{"is_source_file": true, "format": "JSON", "description": "Configuration file for a React project, defining project metadata, dependencies, scripts, ESLint configuration, and browser compatibility.", "external_files": [], "external_methods": [], "published": [], "classes": [], "methods": [], "calls": [], "search-terms": ["react-kavia", "dependencies", "scripts", "eslintConfig", "browserslist"], "state": 2, "file_id": 7, "knowledge_revision": 16, "git_revision": "eeb53e566ce0303a5eef40893236543f16ac9a2e", "hash": "d001d53c059625c4bcf75bf5a7f3fcf0", "format-version": 4, "code-base-name": "frontend", "filename": "frontend/package.json", "revision_history": [{"16": "eeb53e566ce0303a5eef40893236543f16ac9a2e"}]}